llm_utils/__init__.py
llm_utils/py.typed
llm_utils/utils.py
llm_utils-0.2.8.dist-info/METADATA
llm_utils-0.2.8.dist-info/WHEEL
llm_utils-0.2.8.dist-info/licenses/LICENSE
llm_utils-0.2.8.dist-info/RECORD
