Metadata-Version: 2.1
Name: llm-utils
Version: 0.2.8
Summary: Utilities for our LLM projects (CWhy, ChatDBG, ...).
Project-URL: Homepage, https://github.com/plasma-umass/llm-utils
Project-URL: Bug Tracker, https://github.com/plasma-umass/llm-utils/issues
Author-email: Nicolas van Kempen <nvankemp@gmail.com>, Emery Berger <emery.berger@gmail.com>, Sam Stern <sternj@umass.edu>
License-File: LICENSE
Classifier: License :: OSI Approved :: Apache Software License
Classifier: Operating System :: OS Independent
Classifier: Programming Language :: Python :: 3
Requires-Python: >=3.8
Requires-Dist: tiktoken>=0.5.2
